tkauto/__init__.py
tkauto/main.py
tkauto/tkfm_UI.ui
tkauto/data/CharacterInfo.json
tkauto/data/CharacterTag.json
tkauto/data/KorInfo.json
tkauto/data/tags_dictionary.txt
tkauto/module/Capture.py
tkauto/module/FindCharacterByTag.py
tkauto/module/ImgProcessing.py
tkauto/module/TesseractOCR.py
tkauto/module/Util.py
tkauto-1.0.3.dist-info/LICENSE
tkauto-1.0.3.dist-info/METADATA
tkauto-1.0.3.dist-info/WHEEL
tkauto-1.0.3.dist-info/top_level.txt
tkauto-1.0.3.dist-info/RECORD
